vixpy/__init__.py
vixpy/vixpy.py
Vixpy-1.0.0.dist-info/LICENSE
Vixpy-1.0.0.dist-info/METADATA
Vixpy-1.0.0.dist-info/WHEEL
Vixpy-1.0.0.dist-info/top_level.txt
Vixpy-1.0.0.dist-info/RECORD
