Metadata-Version: 2.1
Name: Vixpy
Version: 1.0.0
Summary: Python classes and bindings for VMWare VIX API
Home-page: https://github.com/dshikashio/vixpy
Author: Doug S
License: MIT
Keywords: vmware,vix,automation
Platform: UNKNOWN
Classifier: License :: OSI Approved :: MIT License
Classifier: Programming Language :: Python :: 3
Classifier: Development Status :: 5 - Production/Stable
Classifier: Intended Audience :: Developers
Classifier: Intended Audience :: Science/Research
Classifier: Natural Language :: English
Classifier: Programming Language :: Python
Classifier: Topic :: Software Development :: Libraries :: Python Modules
Requires-Python: >=3.6.0
